pycabfile/__init__.py
pycabfile/cab_reader.py
pycabfile/cab_structs.py
pycabfile/cab_writer.py
pycabfile/cabfile.py
pycabfile/utils.py
test/__init__.py
test/run_all_tests.py
test/test_basic.py
test/test_functional.py
pycabfile-1.0.0.dist-info/METADATA
pycabfile-1.0.0.dist-info/WHEEL
pycabfile-1.0.0.dist-info/entry_points.txt
pycabfile-1.0.0.dist-info/top_level.txt
pycabfile-1.0.0.dist-info/RECORD
