Metadata-Version: 2.1
Name: pycabfile
Version: 1.0.0
Summary: A Python library for handling Microsoft Cabinet files with zipfile-like interface
Home-page: https://github.com/hanul93/pycabfile
Author: Kei Choi
Author-email: hanul93@gmail.com
Project-URL: Bug Reports, https://github.com/hanul93/pycabfile/issues
Project-URL: Source, https://github.com/hanul93/pycabfile
Project-URL: Documentation, https://github.com/hanul93/pycabfile/blob/main/README.md
Keywords: cab cabinet archive compression
Classifier: Development Status :: 4 - Beta
Classifier: Intended Audience :: Developers
Classifier: License :: OSI Approved :: MIT License
Classifier: Operating System :: OS Independent
Classifier: Programming Language :: Python :: 3
Classifier: Programming Language :: Python :: 3.10
Classifier: Programming Language :: Python :: 3.11
Classifier: Programming Language :: Python :: 3.12
Classifier: Topic :: Software Development :: Libraries :: Python Modules
Classifier: Topic :: System :: Archiving :: Compression
Requires-Python: >=3.10
Provides-Extra: dev
Requires-Dist: pytest (>=6.0) ; extra == 'dev'
Requires-Dist: pytest-cov (>=2.0) ; extra == 'dev'
Requires-Dist: black (>=22.0) ; extra == 'dev'
Requires-Dist: flake8 (>=4.0) ; extra == 'dev'
